sodium/__init__.py
sodium/base/__init__.py
sodium/base/base_dataloader.py
sodium/base/base_model.py
sodium/base/base_trainer.py
sodium/data_loader/__init__.py
sodium/data_loader/augmentation.py
sodium/data_loader/data_loaders.py
sodium/gradcam/__init__.py
sodium/gradcam/core.py
sodium/gradcam/gradcam.py
sodium/metrics/__init__.py
sodium/metrics/metrics.py
sodium/model/__init__.py
sodium/model/loss.py
sodium/model/model.py
sodium/model/quiz_dnn.py
sodium/model/resnet.py
sodium/plot/__init__.py
sodium/runner/__init__.py
sodium/trainer/__init__.py
sodium/trainer/trainer.py
sodium/tsai_model/__init__.py
sodium/tsai_model/s8.py
sodium/utils/__init__.py
sodium/utils/config.py
sodium/utils/data.py
sodium/utils/logger.py
py_sodium-0.0.2.dist-info/METADATA
py_sodium-0.0.2.dist-info/WHEEL
py_sodium-0.0.2.dist-info/top_level.txt
py_sodium-0.0.2.dist-info/RECORD
