Metadata-Version: 2.1
Name: py-sodium
Version: 0.0.2
Summary: PySodium
Home-page: https://github.com/satyajitghana/PySodium
Author: Satyajit Ghana
Author-email: satyajitghana7@gmail.com
License: UNKNOWN
Platform: UNKNOWN
Classifier: Programming Language :: Python :: 3
Classifier: License :: OSI Approved :: MIT License
Classifier: Operating System :: OS Independent
Requires-Python: >=3.6
Requires-Dist: tqdm
Requires-Dist: numpy
Requires-Dist: matplotlib
Requires-Dist: torch
Requires-Dist: torchvision
Requires-Dist: albumentations
Requires-Dist: torch-lr-finder
